dist_py_module/__init__.py
dist_py_module/py.typed
dist_py_module/conf/dist_py_module.cfg
dist_py_module/conf/dist_py_module.logo
dist_py_module/conf/dist_py_module_util.cfg
dist_py_module/conf/project.yaml
dist_py_module/conf/template/MANIFEST.template
dist_py_module/conf/template/pyproject.template
dist_py_module/conf/template/setup.template
dist_py_module/conf/template/setup_package.template
dist_py_module/conf/template/setup_tool.template
dist_py_module/log/dist_py_module.log
dist_py_module/pro/__init__.py
dist_py_module/pro/read_template.py
dist_py_module/pro/write_template.py
dist_py_module-3.0.9.dist-info/licenses/LICENSE
usr/local/bin/dist_py_module_run.py
dist_py_module-3.0.9.dist-info/METADATA
dist_py_module-3.0.9.dist-info/WHEEL
dist_py_module-3.0.9.dist-info/top_level.txt
dist_py_module-3.0.9.dist-info/RECORD
