Metadata-Version: 2.4
Name: dist_py_module
Version: 3.0.9
Summary: Python package for generation of setup file
Home-page: https://vroncevic.github.io/dist_py_module
Author: Vladimir Roncevic
Author-email: elektron.ronca@gmail.com
License: GPL-3.0-or-later
Keywords: setup,python,install,dist
Platform: POSIX
Classifier: Programming Language :: Python :: 3.10
Classifier: Programming Language :: Python :: 3.11
Classifier: Programming Language :: Python :: 3.12
License-File: LICENSE
Requires-Dist: ats-utilities
Dynamic: author
Dynamic: author-email
Dynamic: classifier
Dynamic: description
Dynamic: description-content-type
Dynamic: home-page
Dynamic: keywords
Dynamic: license
Dynamic: license-file
Dynamic: platform
Dynamic: requires-dist
Dynamic: summary
